visualapplets.py
visualapplets-1.0.dist-info/LICENSE
visualapplets-1.0.dist-info/METADATA
visualapplets-1.0.dist-info/WHEEL
visualapplets-1.0.dist-info/top_level.txt
visualapplets-1.0.dist-info/RECORD
