Metadata-Version: 2.1
Name: visualapplets
Version: 1.0
Summary: Python bindings for Basler's VisualApplets TCL script generation.
Home-page: https://github.com/jurihock/visualapplets.py
Author: Juergen Hock
Author-email: juergen.hock@jurihock.de
License: MPL-2.0
Keywords: automation,basler,camera,cameralink,dsp,fpga,framegrabber,gigevision,high-performance,image-processing,kintex7,machine-vision,microenable,prototyping,python,real-time,siso,tcl,visualapplets,xilinx
Platform: UNKNOWN
Classifier: Development Status :: 4 - Beta
Classifier: Intended Audience :: Developers
Classifier: Intended Audience :: Manufacturing
Classifier: Intended Audience :: Science/Research
Classifier: License :: OSI Approved :: Mozilla Public License 2.0 (MPL 2.0)
Classifier: Programming Language :: Python :: 3
Classifier: Programming Language :: Tcl
Classifier: Topic :: Scientific/Engineering
Classifier: Topic :: Scientific/Engineering :: Electronic Design Automation (EDA)
Classifier: Topic :: Scientific/Engineering :: Image Processing
Classifier: Topic :: Scientific/Engineering :: Visualization
Classifier: Topic :: Software Development
Classifier: Topic :: Software Development :: Code Generators
Classifier: Topic :: System :: Hardware
Classifier: Topic :: Utilities
License-File: LICENSE
